drymerge/__init__.py
drymerge/client.py
drymerge/identity.py
module/__init__.py
module/client.py
module/identity.py
drymerge-0.1.12.dist-info/METADATA
drymerge-0.1.12.dist-info/WHEEL
drymerge-0.1.12.dist-info/top_level.txt
drymerge-0.1.12.dist-info/RECORD
