Metadata-Version: 2.1
Name: drymerge
Version: 0.1.12
Summary: DryMerge Client SDK.
Author: Samuel Brashears
Author-email: sam@drymerge.com
Requires-Dist: requests
